certreq/__init__.py
certreq/__version__.py
certreq/certreq.py
certreq-0.1.0.dist-info/LICENSE
certreq-0.1.0.dist-info/METADATA
certreq-0.1.0.dist-info/WHEEL
certreq-0.1.0.dist-info/entry_points.txt
certreq-0.1.0.dist-info/top_level.txt
certreq-0.1.0.dist-info/RECORD
