Metadata-Version: 2.1
Name: certreq
Version: 0.1.0
Summary: python implementation of certreq
Home-page: https://github.com/steschuser/certreq
Author: Steffen Schwebel
Author-email: s.schwebel@uvensys.de
License: MIT
Platform: UNKNOWN
Classifier: License :: OSI Approved :: MIT License
Classifier: Programming Language :: Python
Classifier: Programming Language :: Python :: 3
Classifier: Programming Language :: Python :: 3.6
Classifier: Programming Language :: Python :: Implementation :: CPython
Classifier: Programming Language :: Python :: Implementation :: PyPy
Requires-Python: >=3.5.0
Requires-Dist: requests
Requires-Dist: requests-ntlm
Requires-Dist: loguru
Requires-Dist: parse-it
